airflow_plugin_config_storage/__init__.py
airflow_plugin_config_storage/cli.py
airflow_plugin_config_storage-0.1.0.dist-info/LICENSE
airflow_plugin_config_storage-0.1.0.dist-info/METADATA
airflow_plugin_config_storage-0.1.0.dist-info/WHEEL
airflow_plugin_config_storage-0.1.0.dist-info/entry_points.txt
airflow_plugin_config_storage-0.1.0.dist-info/top_level.txt
airflow_plugin_config_storage-0.1.0.dist-info/RECORD
