Metadata-Version: 2.1
Name: airflow-plugin-config-storage
Version: 0.1.0
Summary: Inject connections into the airflow database from configuration
Home-page: https://bliseng.github.io/airflow-plugin-config-storage/
Author: Drew J. Sonne
Author-email: drew.sonne@gmail.com
License: LGPLv3
Platform: UNKNOWN
Requires-Dist: click
Requires-Dist: unidecode
Requires-Dist: apache-airflow
